{
  "strategy_name": "HonestTrendGeneric",
  "params": {
    "roi": {"0": 100},
    "stoploss": {"stoploss": -0.99},
    "max_open_trades": {"max_open_trades": 3},
    "buy": {
      "ema_fast": 1410,
      "ema_slow": 2085,
      "adx_threshold": 18,
      "min_hold_minutes": 1440
    }
  },
  "ft_stratparam_v": 1,
  "_notes": "1m live params: EMA 1410/2085 (~24h/35h). Walk-forward 4/4 positive. Use with config_live_honest1m.json. For 15m dry-run, override via config's strategy_name or create HonestTrendGeneric_15m.json"
}
